{
    "AGGALUT692": {
      "password": "1G5Z1R5O",
      "grade": 87,
      "name": "AGGALUT, JANICE V."
    },
    "AMPOLOQUIO574": {
      "password": "5K3J4Y3N",
      "grade": 90,
      "name": "AMPOLOQUIO, PATRICIA L."
    },
    "ANADIA531": {
      "password": "2B0H3Q0L",
      "grade": 89,
      "name": "ANADIA, RICHELLE, P."
    },
    "AREVALO376": {
      "password": "8C5V1F7W",
      "grade": 88,
      "name": "AREVALO, CRISTHEL D."
    },
    "AUTOR195": {
      "password": "5S9S7D2B",
      "grade": 86,
      "name": "AUTOR, JENIFER JANE L."
    },
    "BARCE248": {
      "password": "9E4D8U0R",
      "grade": 89,
      "name": "BARCE, CHRISTIAN PAUL D."
    },
    "BILLIONES896": {
      "password": "9F3P1K9M",
      "grade": 91,
      "name": "BILLIONES, ALTHEA HILARIE B."
    },
    "BUGAHOD539": {
      "password": "7R0G6X2X",
      "grade": 85,
      "name": "BUGAHOD, STEPHANIE A."
    },
    "CARUPO675": {
      "password": "0K6K0T7Y",
      "grade": 88,
      "name": "CARUPO, ABEGAIL T."
    },
    "CHAVEZ278": {
      "password": "0W9K1X1Z",
      "grade": 87,
      "name": "CHAVEZ, MARIANNE N."
    },
    "COMONAL600": {
      "password": "7Q8X0L8T",
      "grade": 87,
      "name": "COMONAL, KLEENSAY N."
    },
    "CORDERO484": {
      "password": "3L3X4P8S",
      "grade": 87,
      "name": "CORDERO, MARY CLAIRE ANN T."
    },
    "DULLANO210": {
      "password": "2G6D6R6D",
      "grade": 89,
      "name": "DULLANO, KEY D."
    },
    "FABULAR445": {
      "password": "6B4A5W2X",
      "grade": 61,
      "name": "FABULAR, RIZA MAE"
    },
    "GELICAME281": {
      "password": "4T6Z0B3E",
      "grade": 84,
      "name": "GELICAME, JAYM J."
    },
    "HANIBO714": {
      "password": "4W5L9G2V",
      "grade": 88,
      "name": "HANIBO, CHRISTIAN JAY P."
    },
    "LINO790": {
      "password": "7I6B6B4F",
      "grade": 93,
      "name": "LINO, SHAHARAH M."
    },
    "MASLOG651": {
      "password": "6K6T1I1Y",
      "grade": 89,
      "name": "MASLOG, CLAIRE A"
    },
    "MERENCILLO481": {
      "password": "7U1O8Y3A",
      "grade": 89,
      "name": "MERENCILLO, PAMELA JEAN B."
    },
    "NABARES299": {
      "password": "1L1S6M7C",
      "grade": 91,
      "name": "NABARES, JEMAICA D."
    },
    "OCANA182": {
      "password": "0Q6H7Z1X",
      "grade": 89,
      "name": "OCANA, JONEL B."
    },
    "OMOLIAN604": {
      "password": "8Y8G2I8M",
      "grade": 90,
      "name": "OMOLIAN, RUBELYN C."
    },
    "OMOS346": {
      "password": "6C7P0S3Z",
      "grade": 89,
      "name": "OMOS, LARA MAE T."
    },
    "PASUGUIRON312": {
      "password": "1L9L0L1H",
      "grade": 84,
      "name": "PASUGUIRON, CARLO C."
    },
    "PANDIAN345": {
      "password": "1W5U5U9A",
      "grade": 89,
      "name": "PANDIAN, JOANNA MARIE Y."
    },
    "PEROCHO679": {
      "password": "0E4J3X3B",
      "grade": 86,
      "name": "PEROCHO, JUVAN KARL T."
    },
    "PILOTON512": {
      "password": "9X7Z9V2S",
      "grade": 84,
      "name": "PILOTON, SANDIE S."
    },
    "PONCE885": {
      "password": "1T7J7B1T",
      "grade": 88,
      "name": "PONCE, AGATHA CHRISTINE C."
    },
    "RAMOS460": {
      "password": "9Y4V6R5N",
      "grade": 84,
      "name": "RAMOS, JAY L."
    },
    "REBALDE893": {
      "password": "6R9V9C8R",
      "grade": 40,
      "name": "REBALDE, SHARAH JEAN B."
    },
    "RECITAS812": {
      "password": "3B6J8W1Q",
      "grade": 91,
      "name": "RECITAS, RAYMOND T."
    },
    "REN501": {
      "password": "6C1D5S1Q",
      "grade": 93,
      "name": "REN, JEANY ANN Y."
    },
    "SUMALHAG709": {
      "password": "3D8F5L0Y",
      "grade": 89,
      "name": "SUMALHAG, KAREN P."
    },
    "SUMALHAG842": {
      "password": "3U7Z3Y9O",
      "grade": 87,
      "name": "SUMALHAG, KENETH JOY, M."
    }
  }
  